[
    {
        "type": 1,
        "textQue": "Кто этот футболист?",
        "slugQue": "cska_musaev",
        "comment": "23-летний (29.07.2001) российский нападающий. Перешёл в ЦСКА зимой 2024 из Балтики",
        "slugDlg": "cska_musaev",
        "slugCorAns": "no_pic",
        "txtCorAns": "Тамерлан Мусаев",
        "wrSlgAns1": "no_pic",
        "wrTxtAns1": "Артем Бандикян",
        "wrSlgAns2": "no_pic",
        "wrTxtAns2": "Аббосбек Файзулаев",
        "wrSlgAns3": "no_pic",
        "wrTxtAns3": "Артем Шуманский",
        "wrSlgAns4": "no_pic",
        "wrTxtAns4": "Матвей Кисляк",
        "wrSlgAns5": "no_pic",
        "wrTxtAns5": "Николай Баровский"
    },
    {
        "type": 1,
        "textQue": "Кто этот футболист?",
        "slugQue": "cska_faizulaev",
        "comment": "20-летний (03.10.2003) узбекский нападающий. Перешёл в ЦСКА летом 2023 из Пахтакора",
        "slugDlg": "cska_faizulaev",
        "slugCorAns": "no_pic",
        "txtCorAns": "Аббосбек Файзулаев",
        "wrSlgAns1": "no_pic",
        "wrTxtAns1": "Кристиян Бистрович",
        "wrSlgAns2": "no_pic",
        "wrTxtAns2": "Саша Здьелар",
        "wrSlgAns3": "no_pic",
        "wrTxtAns3": "Милан Гайич",
        "wrSlgAns4": "no_pic",
        "wrTxtAns4": "Артем Шуманский",
        "wrSlgAns5": "no_pic",
        "wrTxtAns5": "Артем Бандикян"
    },
    {
        "type": 1,
        "textQue": "Кто этот футболист?",
        "slugQue": "cska_krugovoj",
        "comment": "Защитник",
        "slugDlg": "cska_krugovoj",
        "slugCorAns": "no_pic",
        "txtCorAns": "Данил Круговой",
        "wrSlgAns1": "no_pic",
        "wrTxtAns1": "Максим Мухин",
        "wrSlgAns2": "no_pic",
        "wrTxtAns2": "Артем Шуманский",
        "wrSlgAns3": "no_pic",
        "wrTxtAns3": "Тамерлан Мусаев",
        "wrSlgAns4": "no_pic",
        "wrTxtAns4": "Матвей Кисляк",
        "wrSlgAns5": "no_pic",
        "wrTxtAns5": "Милан Гайич"
    },
    {
        "type": 1,
        "textQue": "Кто этот футболист?",
        "slugQue": "https://amaranth64.github.io/RPL_V2/matchday/images/sm_mangash.jpg",
        "comment": "Защитник",
        "slugDlg": "https://amaranth64.github.io/RPL_V2/matchday/images/sm_mangash.jpg",
        "slugCorAns": "no_pic",
        "txtCorAns": "Рикарду Мангаш",
        "wrSlgAns1": "no_pic",
        "wrTxtAns1": "Эсекиэль Барко",
        "wrSlgAns2": "no_pic",
        "wrTxtAns2": "Виллиан Жозе",
        "wrSlgAns3": "no_pic",
        "wrTxtAns3": "Манфред Угальде",
        "wrSlgAns4": "no_pic",
        "wrTxtAns4": "Тео Бонгонда",
        "wrSlgAns5": "no_pic",
        "wrTxtAns5": "Томаш Тавареш"
    },
    {
        "type": 1,
        "textQue": "Кто этот футболист?",
        "slugQue": "sm_abena",
        "comment": "Защитник",
        "slugDlg": "sm_abena",
        "slugCorAns": "no_pic",
        "txtCorAns": "Абена Миенти",
        "wrSlgAns1": "no_pic",
        "wrTxtAns1": "Хесус Медина",
        "wrSlgAns2": "no_pic",
        "wrTxtAns2": "Манфред Угальде",
        "wrSlgAns3": "no_pic",
        "wrTxtAns3": "Даниил Хлусевич",
        "wrSlgAns4": "no_pic",
        "wrTxtAns4": "Олег Рябчук",
        "wrSlgAns5": "no_pic",
        "wrTxtAns5": "Томаш Тавареш"
    },
    {
        "type": 1,
        "textQue": "Кто этот футболист?",
        "slugQue": "sm_markinios",
        "comment": "Фланговый нападающий",
        "slugDlg": "sm_markinios",
        "slugCorAns": "no_pic",
        "txtCorAns": "Маркиньос",
        "wrSlgAns1": "no_pic",
        "wrTxtAns1": "Виллиан Жозе",
        "wrSlgAns2": "no_pic",
        "wrTxtAns2": "Шамар Николсон",
        "wrSlgAns3": "no_pic",
        "wrTxtAns3": "Алексис Дуарте",
        "wrSlgAns4": "no_pic",
        "wrTxtAns4": "Томаш Тавареш",
        "wrSlgAns5": "no_pic",
        "wrTxtAns5": "Срджан Бабич"
    },
    {
        "type": 2,
        "textQue": "С кем сыграет ЦСКА в следующем туре?",
        "slugQue": "logo_cska",
        "comment": "10.11. 13:00. Самара Арена",
        "slugDlg": "logo_ks",
        "slugCorAns": "logo_ks",
        "txtCorAns": "Крылья Советов",
        "wrSlgAns1": "logo_pari",
        "wrTxtAns1": "Пари НН",
        "wrSlgAns2": "logo_dinamo",
        "wrTxtAns2": "Динамо Москва",
        "wrSlgAns3": "logo_dinamo_mah",
        "wrTxtAns3": "Динамо Махачкала",
        "wrSlgAns4": "logo_lokomotiv",
        "wrTxtAns4": "Локомотив Москва",
        "wrSlgAns5": "logo_rubin",
        "wrTxtAns5": "Рубин Казань"
    },
    {
        "type": 2,
        "textQue": "С кем сыграет Спартак в следующем туре?",
        "slugQue": "logo_spartak",
        "comment": "11.11. 17:15. Лукоил Арена",
        "slugDlg": "logo_akron",
        "slugCorAns": "logo_akron",
        "txtCorAns": "Акрон",
        "wrSlgAns1": "logo_fakel",
        "wrTxtAns1": "Факел",
        "wrSlgAns2": "logo_orenburg",
        "wrTxtAns2": "Оренбург",
        "wrSlgAns3": "logo_zenit",
        "wrTxtAns3": "Зенит",
        "wrSlgAns4": "logo_khimki",
        "wrTxtAns4": "Химки",
        "wrSlgAns5": "logo_akhmat",
        "wrTxtAns5": "Ахмат"
    },
    {
        "type": 2,
        "textQue": "С какой командой играл ЦСКА в прошлом туре?",
        "slugQue": "logo_cska",
        "comment": "ЦСКА 0:0 Факел",
        "slugDlg": "logo_fakel",
        "slugCorAns": "logo_fakel",
        "txtCorAns": "Факел",
        "wrSlgAns1": "logo_akron",
        "wrTxtAns1": "Акрон",
        "wrSlgAns2": "logo_orenburg",
        "wrTxtAns2": "Оренбург",
        "wrSlgAns3": "logo_zenit",
        "wrTxtAns3": "Зенит",
        "wrSlgAns4": "logo_khimki",
        "wrTxtAns4": "Химки",
        "wrSlgAns5": "logo_akhmat",
        "wrTxtAns5": "Ахмат"
    },
    {
        "type": 2,
        "textQue": "У кого выиграл Спартак в прошлом туре?",
        "slugQue": "logo_spartak",
        "comment": "Пари НН 0:2 Спартак (Т. Бонгонда 68', Ш. Николсон 90+2')",
        "slugDlg": "logo_pari",
        "slugCorAns": "logo_pari",
        "txtCorAns": "Пари НН",
        "wrSlgAns1": "logo_ks",
        "wrTxtAns1": "Крылья Советов",
        "wrSlgAns2": "logo_dinamo",
        "wrTxtAns2": "Динамо Москва",
        "wrSlgAns3": "logo_dinamo_mah",
        "wrTxtAns3": "Динамо Махачкала",
        "wrSlgAns4": "logo_lokomotiv",
        "wrTxtAns4": "Локомотив Москва",
        "wrSlgAns5": "logo_rubin",
        "wrTxtAns5": "Рубин Казань"
    },
    {
        "type": 1,
        "textQue": "Кто из этих игроков играл и за Спартак, и за ЦСКА?",
        "slugQue": "https://amaranth64.github.io/RPL_V2/matchday/images/mt_spartak_cska_quest.jpg",
        "comment": "",
        "slugDlg": "ro_karpin",
        "slugCorAns": "no_pic",
        "txtCorAns": "Валерий Карпин",
        "wrSlgAns1": "no_pic",
        "wrTxtAns1": "Луис Робсон",
        "wrSlgAns2": "no_pic",
        "wrTxtAns2": "Андрей Тихонов",
        "wrSlgAns3": "no_pic",
        "wrTxtAns3": "Николай Писарев",
        "wrSlgAns4": "no_pic",
        "wrTxtAns4": "Виктор Онопко",
        "wrSlgAns5": "no_pic",
        "wrTxtAns5": "Александр Филимонов"
    },
    {
        "type": 1,
        "textQue": "Кто из этих игроков играл и за ЦСКА, и за Спартак?",
        "slugQue": "https://amaranth64.github.io/RPL_V2/matchday/images/mt_spartak_cska_quest.jpg",
        "comment": "",
        "slugDlg": "https://amaranth64.github.io/RPL_V2/matchday/images/mt_spartak_cska_quest.jpg",
        "slugCorAns": "no_pic",
        "txtCorAns": "Руслан Нигматуллин",
        "wrSlgAns1": "no_pic",
        "wrTxtAns1": "Вениамин Мандрыкин",
        "wrSlgAns2": "no_pic",
        "wrTxtAns2": "Веллитон",
        "wrSlgAns3": "no_pic",
        "wrTxtAns3": "Дмитрий Торбинский",
        "wrSlgAns4": "no_pic",
        "wrTxtAns4": "Георгий Щенников",
        "wrSlgAns5": "no_pic",
        "wrTxtAns5": "Евгений Алдонин"
    },
    {
        "type": 1,
        "textQue": "Как зовут главного тренера Спартака?",
        "slugQue": "sm_stankovich",
        "comment": "46-летний главный тренер Спартака с начала сезона 2024/25",
        "slugDlg": "sm_stankovich",
        "slugCorAns": "no_pic",
        "txtCorAns": "Деян Станкович",
        "wrSlgAns1": "no_pic",
        "wrTxtAns1": "Владимир Слишкович",
        "wrSlgAns2": "no_pic",
        "wrTxtAns2": "Доменико Тедеско",
        "wrSlgAns3": "no_pic",
        "wrTxtAns3": "Димитр Димитров",
        "wrSlgAns4": "no_pic",
        "wrTxtAns4": "Владимир Вайсс",
        "wrSlgAns5": "no_pic",
        "wrTxtAns5": "Миодраг Божович"
    },
    {
        "type": 1,
        "textQue": "Как зовут главного тренера ЦСКА?",
        "slugQue": "cska_nikolich",
        "comment": "Главный тренер ЦСКА с 2024 года",
        "slugDlg": "cska_nikolich",
        "slugCorAns": "no_pic",
        "txtCorAns": "Марко Николич",
        "wrSlgAns1": "no_pic",
        "wrTxtAns1": "Мирча Луческу",
        "wrSlgAns2": "no_pic",
        "wrTxtAns2": "Славолюб Муслин",
        "wrSlgAns3": "no_pic",
        "wrTxtAns3": "Владимир Ивич",
        "wrSlgAns4": "no_pic",
        "wrTxtAns4": "Саша Илич",
        "wrSlgAns5": "no_pic",
        "wrTxtAns5": "Ивица Олич"
    },
    {
        "type": 2,
        "textQue": "Кто из текущих игроков ЦСКА дольше всех находится в клубе?",
        "slugQue": "logo_cska",
        "comment": "В команде с 2003 года. Воспитанник",
        "slugDlg": "cska_akinfeev",
        "slugCorAns": "cska_akinfeev",
        "txtCorAns": "Игорь Акинфеев",
        "wrSlgAns1": "cska_diveev",
        "wrTxtAns1": "Игорь Дивеев",
        "wrSlgAns2": "cska_obljakov",
        "wrTxtAns2": "Иван Обляков",
        "wrSlgAns3": "cska_musaev",
        "wrTxtAns3": "Тамерлан Мусаев",
        "wrSlgAns4": "cska_krugovoj",
        "wrTxtAns4": "Данил Круговой",
        "wrSlgAns5": "cska_zdelar",
        "wrTxtAns5": "Саша Здьелар"
    },
    {
        "type": 2,
        "textQue": "Кто из текущих игроков Спартака дольше всех находится в клубе?",
        "slugQue": "logo_spartak",
        "comment": "В команде с 1 июля 2016 года",
        "slugDlg": "sm_zobnin",
        "slugCorAns": "sm_zobnin",
        "txtCorAns": "Роман Зобнин",
        "wrSlgAns1": "sm_umjarov",
        "wrTxtAns1": "Наиль Умяров",
        "wrSlgAns2": "sm_duarte",
        "wrTxtAns2": "Алексис Дуарте",
        "wrSlgAns3": "sm_hlusevich",
        "wrTxtAns3": "Даниил Хлусевич",
        "wrSlgAns4": "sm_maksimenko",
        "wrTxtAns4": "Александр Максименко",
        "wrSlgAns5": "sm_selihov",
        "wrTxtAns5": "Александр Селихов"
    },
    {
        "type": 2,
        "textQue": "Кто является лучшим бомбардиром ЦСКА в этом сезоне РПЛ?",
        "slugQue": "logo_cska",
        "comment": "6 голов в 12 матчах",
        "slugDlg": "cska_musaev",
        "slugCorAns": "cska_musaev",
        "txtCorAns": "Тамерлан Мусаев",
        "wrSlgAns1": "cska_diveev",
        "wrTxtAns1": "Игорь Дивеев",
        "wrSlgAns2": "cska_krugovoj",
        "wrTxtAns2": "Данил Круговой",
        "wrSlgAns3": "cska_zdelar",
        "wrTxtAns3": "Саша Здьелар",
        "wrSlgAns4": "cska_bistrovich",
        "wrTxtAns4": "Кристиян Бистрович",
        "wrSlgAns5": "cska_faizulaev",
        "wrTxtAns5": "Аббосбек Файзулаев"
    },
    {
        "type": 2,
        "textQue": "Кто является лучшим бомбардиром Спартака в этом сезоне РПЛ?",
        "slugQue": "logo_spartak",
        "comment": "6 голов в 12 матчах",
        "slugDlg": "sm_ugalde",
        "slugCorAns": "sm_ugalde",
        "txtCorAns": "Манфред Угальде",
        "wrSlgAns1": "sm_barko",
        "wrTxtAns1": "Эсекиэль Барко",
        "wrSlgAns2": "sm_bongonda",
        "wrTxtAns2": "Тео Бонгонда",
        "wrSlgAns3": "sm_zobnin",
        "wrTxtAns3": "Роман Зобнин",
        "wrSlgAns4": "sm_zinkovskij",
        "wrTxtAns4": "Антон Зиньковский",
        "wrSlgAns5": "sm_zhoze",
        "wrTxtAns5": "Виллиан Жозе"
    },
    {
        "type": 4,
        "textQue": "На каком месте находится ЦСКА после тринадцати туров?",
        "slugQue": "logo_cska",
        "comment": "24 очка",
        "slugDlg": "logo_cska",
        "slugCorAns": "num_5",
        "txtCorAns": "На 5 месте",
        "wrSlgAns1": "num_2",
        "wrTxtAns1": "На 2 месте",
        "wrSlgAns2": "num_3",
        "wrTxtAns2": "На 3 месте",
        "wrSlgAns3": "num_4",
        "wrTxtAns3": "На 4 месте",
        "wrSlgAns4": "num_7",
        "wrTxtAns4": "На 7 месте",
        "wrSlgAns5": "num_6",
        "wrTxtAns5": "На 6 месте"
    },
    {
        "type": 4,
        "textQue": "На каком месте находится Спартак после тринадцати туров?",
        "slugQue": "logo_spartak",
        "comment": "22 очка",
        "slugDlg": "logo_spartak",
        "slugCorAns": "num_6",
        "txtCorAns": "На 6 месте",
        "wrSlgAns1": "num_8",
        "wrTxtAns1": "На 8 месте",
        "wrSlgAns2": "num_3",
        "wrTxtAns2": "На 3 месте",
        "wrSlgAns3": "num_4",
        "wrTxtAns3": "На 4 месте",
        "wrSlgAns4": "num_5",
        "wrTxtAns4": "На 5 месте",
        "wrSlgAns5": "num_7",
        "wrTxtAns5": "На 7 месте"
    },
    {
        "type": 1,
        "textQue": "Кто этот знаменитый футболист, игрок ЦСКА в прошлом?",
        "slugQue": "https://amaranth64.github.io/RPL_V2/matchday/images/cska_pontus.jpg",
        "comment": "ЦСКА (2012 - 2018)",
        "slugDlg": "https://amaranth64.github.io/RPL_V2/matchday/images/cska_pontus.jpg",
        "slugCorAns": "no_pic",
        "txtCorAns": "Понтус Вернблум",
        "wrSlgAns1": "no_pic",
        "wrTxtAns1": "Георги Миланов",
        "wrSlgAns2": "no_pic",
        "wrTxtAns2": "Зоран Тошич",
        "wrSlgAns3": "no_pic",
        "wrTxtAns3": "Александр Цауня",
        "wrSlgAns4": "no_pic",
        "wrTxtAns4": "Карлос Страндберг",
        "wrSlgAns5": "no_pic",
        "wrTxtAns5": "Бибрас Натхо"
    },
    {
        "type": 1,
        "textQue": "Кто этот знаменитый футболист, игрок Спартака в прошлом?",
        "slugQue": "https://amaranth64.github.io/RPL_V2/matchday/images/sm_boketti.jpg",
        "comment": "Спартак (2013 - 2019)",
        "slugDlg": "https://amaranth64.github.io/RPL_V2/matchday/images/sm_boketti.jpg",
        "slugCorAns": "no_pic",
        "txtCorAns": "Сальваторе Боккетти",
        "wrSlgAns1": "no_pic",
        "wrTxtAns1": "Патрик Эберт",
        "wrSlgAns2": "no_pic",
        "wrTxtAns2": "Тино Коста",
        "wrSlgAns3": "no_pic",
        "wrTxtAns3": "Хуан Инсаурральде",
        "wrSlgAns4": "no_pic",
        "wrTxtAns4": "Ким Чельстрём",
        "wrSlgAns5": "no_pic",
        "wrTxtAns5": "Ромуло"
    },
    {
        "type": 1,
        "textQue": "С каким счетом завершилась для ЦСКА встреча с Факелом  в прошлом туре?",
        "slugQue": "logo_cska",
        "comment": "ЦСКА 0:0 Факел",
        "slugDlg": "logo_cska",
        "slugCorAns": "no_pic",
        "txtCorAns": "ЦСКА 0:0 Факел",
        "wrSlgAns1": "no_pic",
        "wrTxtAns1": "ЦСКА 1:0 Факел",
        "wrSlgAns2": "no_pic",
        "wrTxtAns2": "ЦСКА 2:0 Факел",
        "wrSlgAns3": "no_pic",
        "wrTxtAns3": "ЦСКА 3:0 Факел",
        "wrSlgAns4": "no_pic",
        "wrTxtAns4": "ЦСКА 1:1 Факел",
        "wrSlgAns5": "no_pic",
        "wrTxtAns5": "ЦСКА 0:1 Факел"
    },
    {
        "type": 1,
        "textQue": "С каким счетом завершилась для Спартака встреча с Пари НН в прошлом туре?",
        "slugQue": "logo_spartak",
        "comment": "Пари НН 0:2 Спартак (Т. Бонгонда 68', Ш. Николсон 90+2')",
        "slugDlg": "logo_spartak",
        "slugCorAns": "no_pic",
        "txtCorAns": "Пари НН 0:2 Спартак",
        "wrSlgAns1": "no_pic",
        "wrTxtAns1": "Пари НН 0:3 Спартак",
        "wrSlgAns2": "no_pic",
        "wrTxtAns2": "Пари НН 1:2 Спартак",
        "wrSlgAns3": "no_pic",
        "wrTxtAns3": "Пари НН 2:2 Спартак",
        "wrSlgAns4": "no_pic",
        "wrTxtAns4": "Пари НН 1:0 Спартак",
        "wrSlgAns5": "no_pic",
        "wrTxtAns5": "Пари НН 0:4 Спартак"
    },
    {
        "type": 1,
        "textQue": "Когда состоялся первый матч между ЦСКА и Спартаком?",
        "slugQue": "https://amaranth64.github.io/RPL_V2/matchday/images/mt_spartak_cska_quest.jpg",
        "comment": "Чемпионат Москвы, весна, 25.05.1924",
        "slugDlg": "https://amaranth64.github.io/RPL_V2/matchday/images/mt_spartak_cska_quest.jpg",
        "slugCorAns": "no_pic",
        "txtCorAns": "25 мая 1924 года",
        "wrSlgAns1": "no_pic",
        "wrTxtAns1": "11 августа 1973 года",
        "wrSlgAns2": "no_pic",
        "wrTxtAns2": "11 июня 1904 года",
        "wrSlgAns3": "no_pic",
        "wrTxtAns3": "3 сентября 1966 года",
        "wrSlgAns4": "no_pic",
        "wrTxtAns4": "25 апреля 1934 года",
        "wrSlgAns5": "no_pic",
        "wrTxtAns5": "25 мая 1946 года"
    },
    {
        "type": 1,
        "textQue": "Кто является самым результативным бомбардиром в российской истории ЦСКА?",
        "slugQue": "logo_cska",
        "comment": "Лучшим бомбардиром в российской истории ЦСКА является Вагнер Лав.  На его счету 85 голов за 9 сезонов в составе армейцев",
        "slugDlg": "cska_vagnerlove",
        "slugCorAns": "no_pic",
        "txtCorAns": "Вагнер Лав",
        "wrSlgAns1": "no_pic",
        "wrTxtAns1": "Сергей Семак",
        "wrSlgAns2": "no_pic",
        "wrTxtAns2": "Фёдор Чалов",
        "wrSlgAns3": "no_pic",
        "wrTxtAns3": "Сейду Думбия",
        "wrSlgAns4": "no_pic",
        "wrTxtAns4": "Алан Дзагоев",
        "wrSlgAns5": "no_pic",
        "wrTxtAns5": "Ахмед Муса"
    },
    {
        "type": 1,
        "textQue": "Кто был первым иностранцев, сыгравшим и за Спартак, и за ЦСКА?",
        "slugQue": "https://amaranth64.github.io/RPL_V2/matchday/images/mt_spartak_cska_quest.jpg",
        "comment": "",
        "slugDlg": "https://amaranth64.github.io/RPL_V2/matchday/images/cska_samaroni.jpg",
        "slugCorAns": "no_pic",
        "txtCorAns": "Леандро Самарони",
        "wrSlgAns1": "no_pic",
        "wrTxtAns1": "Луис Робсон",
        "wrSlgAns2": "no_pic",
        "wrTxtAns2": "Пениче",
        "wrSlgAns3": "no_pic",
        "wrTxtAns3": "Милан Йович",
        "wrSlgAns4": "no_pic",
        "wrTxtAns4": "Жерри-Кристиан Тчуйсе",
        "wrSlgAns5": "no_pic",
        "wrTxtAns5": "Маркао"
    },
    {
        "type": 1,
        "textQue": "Кто является лучшим бомбардиром в истории этого дерби?",
        "slugQue": "https://amaranth64.github.io/RPL_V2/matchday/images/mt_spartak_cska_quest.jpg",
        "comment": "Лучший бомбардир в истории дерби — армеец Вагнер Лав, забивший 9 голов. У Спартака 7 мячей забил Сергей Сальников.",
        "slugDlg": "logo_cska",
        "slugCorAns": "no_pic",
        "txtCorAns": "Вагнер Лав",
        "wrSlgAns1": "no_pic",
        "wrTxtAns1": "Денис Глушаков",
        "wrSlgAns2": "no_pic",
        "wrTxtAns2": "Квинси Промес",
        "wrSlgAns3": "no_pic",
        "wrTxtAns3": "Ахмед Муса",
        "wrSlgAns4": "no_pic",
        "wrTxtAns4": "Сейду Думбия",
        "wrSlgAns5": "no_pic",
        "wrTxtAns5": "Антон Заболотный"
    },
    {
        "type": 1,
        "textQue": "Кто из этих  игроков играл и за Спартак, и за ЦСКА?",
        "slugQue": "https://amaranth64.github.io/RPL_V2/matchday/images/mt_spartak_cska_quest.jpg",
        "comment": "",
        "slugDlg": "https://amaranth64.github.io/RPL_V2/matchday/images/mt_spartak_cska_quest.jpg",
        "slugCorAns": "no_pic",
        "txtCorAns": "Роман Ерёменко",
        "wrSlgAns1": "no_pic",
        "wrTxtAns1": "Юра Мовсисян",
        "wrSlgAns2": "no_pic",
        "wrTxtAns2": "Марек Сухи",
        "wrSlgAns3": "no_pic",
        "wrTxtAns3": "Элвер Рахимич",
        "wrSlgAns4": "no_pic",
        "wrTxtAns4": "Кейсуке Хонда",
        "wrSlgAns5": "no_pic",
        "wrTxtAns5": "Андрей Дикань"
    },
    {
        "type": 2,
        "textQue": "Кто из этих действующих игроков Спартака играл за ЦСКА?",
        "slugQue": "https://amaranth64.github.io/RPL_V2/matchday/images/mt_spartak_cska_quest.jpg",
        "comment": "",
        "slugDlg": "sm_medina",
        "slugCorAns": "sm_medina",
        "txtCorAns": "Хесус Медина",
        "wrSlgAns1": "sm_ugalde",
        "wrTxtAns1": "Манфред Угальде",
        "wrSlgAns2": "sm_markinios",
        "wrTxtAns2": "Маркиньос",
        "wrSlgAns3": "sm_rjabchuk",
        "wrTxtAns3": "Олег Рябчук",
        "wrSlgAns4": "sm_hlusevich",
        "wrTxtAns4": "Даниил Хлусевич",
        "wrSlgAns5": "sm_babich",
        "wrTxtAns5": "Срджан Бабич"
    },
    {
        "type": 1,
        "textQue": "Кто был капитаном Спартака в их последний чемпионский сезон?",
        "slugQue": "logo_spartak",
        "comment": "2016/17",
        "slugDlg": "logo_spartak",
        "slugCorAns": "no_pic",
        "txtCorAns": "Денис Глушаков",
        "wrSlgAns1": "no_pic",
        "wrTxtAns1": "Роман Зобнин",
        "wrSlgAns2": "no_pic",
        "wrTxtAns2": "Георгий Джикия",
        "wrSlgAns3": "no_pic",
        "wrTxtAns3": "Артём Ребров",
        "wrSlgAns4": "no_pic",
        "wrTxtAns4": "Квинси Промес",
        "wrSlgAns5": "no_pic",
        "wrTxtAns5": "Айртон Лукас"
    },
    {
        "type": 1,
        "textQue": "Кто был тренером ЦСКА в их последний чемпионский сезон?",
        "slugQue": "logo_cska",
        "comment": "2015/16",
        "slugDlg": "cska_sluzky",
        "slugCorAns": "no_pic",
        "txtCorAns": "Леонид Слуцкий",
        "wrSlgAns1": "no_pic",
        "wrTxtAns1": "Виктор Гончаренко",
        "wrSlgAns2": "no_pic",
        "wrTxtAns2": "Хуанде Рамос ",
        "wrSlgAns3": "no_pic",
        "wrTxtAns3": "Валерий Газзаев ",
        "wrSlgAns4": "no_pic",
        "wrTxtAns4": "Ивица Олич",
        "wrSlgAns5": "no_pic",
        "wrTxtAns5": "Артур Жорже "
    },
    {
        "type": 1,
        "textQue": "Кто из бывших игроков Спартака является членом списка ФИФА 100?",
        "slugQue": "logo_spartak",
        "comment": "Ринат Дасаев находится на 27 месте среди лучших футболистов всех времен по мнению легенды Пеле",
        "slugDlg": "logo_spartak",
        "slugCorAns": "no_pic",
        "txtCorAns": "Ринат Дасаев",
        "wrSlgAns1": "no_pic",
        "wrTxtAns1": "Валерий Карпин",
        "wrSlgAns2": "no_pic",
        "wrTxtAns2": "Александр Мостовой",
        "wrSlgAns3": "no_pic",
        "wrTxtAns3": "Дмитрий Аленичев",
        "wrSlgAns4": "no_pic",
        "wrTxtAns4": "Виктор Онопко",
        "wrSlgAns5": "no_pic",
        "wrTxtAns5": "Андрей Старостин"
    },
    {
        "type": 1,
        "textQue": "Какое название закрепилось за противостоянием этих двух команд?",
        "slugQue": "https://amaranth64.github.io/RPL_V2/matchday/images/mt_spartak_cska_quest.jpg",
        "comment": "",
        "slugDlg": "https://amaranth64.github.io/RPL_V2/matchday/images/mt_spartak_cska_quest.jpg",
        "slugCorAns": "no_pic",
        "txtCorAns": "«Дерби всея Руси»",
        "wrSlgAns1": "no_pic",
        "wrTxtAns1": "«Дерби двух армий»",
        "wrSlgAns2": "no_pic",
        "wrTxtAns2": "«Московское сражение»",
        "wrSlgAns3": "no_pic",
        "wrTxtAns3": "«Великое московское дерби»",
        "wrSlgAns4": "no_pic",
        "wrTxtAns4": "«Битва за сердце Москвы»",
        "wrSlgAns5": "no_pic",
        "wrTxtAns5": "«Традиция московского футбола»"
    }
]